setup.py
Taxes/__init__.py
Taxes/main.py
taxes_Marjo.egg-info/PKG-INFO
taxes_Marjo.egg-info/SOURCES.txt
taxes_Marjo.egg-info/dependency_links.txt
taxes_Marjo.egg-info/top_level.txt