Metadata-Version: 2.1
Name: taxes-Marjo
Version: 1.0.0
Summary: A package that generate taxes based on the salary
Author: Marjol Mata
Author-email: <marjolmata29@gmail.com>
Keywords: Taxes,tax
Classifier: Development Status :: 1 - Planning
Classifier: Intended Audience :: Developers
Classifier: Programming Language :: Python :: 3
Classifier: Operating System :: Unix
Classifier: Operating System :: MacOS :: MacOS X
Classifier: Operating System :: Microsoft :: Windows
